rlberry/__init__.py
rlberry/agents/__init__.py
rlberry/agents/agent.py
rlberry/agents/stable_baselines/__init__.py
rlberry/agents/stable_baselines/stable_baselines.py
rlberry/agents/tests/__init__.py
rlberry/agents/tests/test_replay.py
rlberry/agents/tests/test_stable_baselines.py
rlberry/agents/utils/__init__.py
rlberry/agents/utils/replay.py
rlberry/agents/utils/replay_utils.py
rlberry/check_packages.py
rlberry/envs/__init__.py
rlberry/envs/basewrapper.py
rlberry/envs/finite_mdp.py
rlberry/envs/gym_make.py
rlberry/envs/interface/__init__.py
rlberry/envs/interface/model.py
rlberry/envs/pipeline.py
rlberry/envs/tests/__init__.py
rlberry/envs/tests/test_env_seeding.py
rlberry/envs/tests/test_gym_env_seeding.py
rlberry/envs/tests/test_gym_make.py
rlberry/envs/utils.py
rlberry/experiment/__init__.py
rlberry/experiment/generator.py
rlberry/experiment/load_results.py
rlberry/experiment/tests/params_experiment.yaml
rlberry/experiment/tests/room.yaml
rlberry/experiment/tests/rsucbvi.yaml
rlberry/experiment/tests/rsucbvi_alternative.yaml
rlberry/experiment/tests/test_experiment_generator.py
rlberry/experiment/tests/test_load_results.py
rlberry/experiment/yaml_utils.py
rlberry/manager/__init__.py
rlberry/manager/comparison.py
rlberry/manager/evaluation.py
rlberry/manager/experiment_manager.py
rlberry/manager/multiple_managers.py
rlberry/manager/plotting.py
rlberry/manager/tests/__init__.py
rlberry/manager/tests/test_comparisons.py
rlberry/manager/tests/test_experiment_manager.py
rlberry/manager/tests/test_experiment_manager_seeding.py
rlberry/manager/tests/test_hyperparam_optim.py
rlberry/manager/tests/test_plot.py
rlberry/manager/tests/test_shared_data.py
rlberry/manager/utils.py
rlberry/metadata_utils.py
rlberry/rendering/__init__.py
rlberry/rendering/common_shapes.py
rlberry/rendering/core.py
rlberry/rendering/opengl_render2d.py
rlberry/rendering/pygame_render2d.py
rlberry/rendering/render_interface.py
rlberry/rendering/tests/__init__.py
rlberry-0.7.3.dist-info/LICENSE
rlberry-0.7.3.dist-info/METADATA
rlberry-0.7.3.dist-info/WHEEL
rlberry-0.7.3.dist-info/RECORD
