Metadata-Version: 2.1
Name: rlberry
Version: 0.7.3
Summary: An easy-to-use reinforcement learning library for research and education
Home-page: https://github.com/rlberry-py
License: LICENSE
Author: Omar Darwiche Domingues, Yannis Flet-Berliac, Edouard Leurent, Pierre Menard, Xuedong Shang
Requires-Python: >=3.9,<3.13
Classifier: Development Status :: 4 - Beta
Classifier: Intended Audience :: Education
Classifier: Intended Audience :: Science/Research
Classifier: License :: OSI Approved :: MIT License
Classifier: License :: Other/Proprietary License
Classifier: Operating System :: OS Independent
Classifier: Programming Language :: Python :: 3
Classifier: Programming Language :: Python :: 3.9
Classifier: Programming Language :: Python :: 3.10
Classifier: Programming Language :: Python :: 3.11
Classifier: Programming Language :: Python :: 3.12
Classifier: Programming Language :: Python :: 3 :: Only
Classifier: Topic :: Scientific/Engineering :: Artificial Intelligence
Provides-Extra: doc
Provides-Extra: extras
Provides-Extra: torch
Requires-Dist: adastop
Requires-Dist: ale-py ; extra == "torch"
Requires-Dist: dill
Requires-Dist: docopt
Requires-Dist: fdasrsf (==2.5.2)
Requires-Dist: ffmpeg-python ; extra == "extras"
Requires-Dist: gymnasium[accept-rom-license,atari] (>=0.29.1,<0.30.0)
Requires-Dist: matplotlib ; extra == "doc"
Requires-Dist: moviepy
Requires-Dist: multimethod (==1.10)
Requires-Dist: myst-parser (>=2.0.0,<3.0.0) ; extra == "doc"
Requires-Dist: numpydoc (>=1.6.0,<2.0.0) ; extra == "doc"
Requires-Dist: opencv-python ; extra == "torch"
Requires-Dist: optuna ; extra == "extras"
Requires-Dist: pandas
Requires-Dist: pygame-ce
Requires-Dist: pyopengl
Requires-Dist: pyyaml
Requires-Dist: scikit-fda (>=0.9,<0.10) ; extra == "extras"
Requires-Dist: scipy
Requires-Dist: sphinx (==6.2.1) ; extra == "doc"
Requires-Dist: sphinx-gallery (>=0.14.0,<0.15.0) ; extra == "doc"
Requires-Dist: sphinx-math-dollar (>=1.2.1,<2.0.0) ; extra == "doc"
Requires-Dist: sphinxcontrib-video (==0.2.0) ; extra == "doc"
Requires-Dist: stable-baselines3 ; extra == "torch"
Requires-Dist: tensorboard ; extra == "torch"
Requires-Dist: torch (>=2.0.0,!=2.0.1,!=2.1.0) ; extra == "torch"
Requires-Dist: tqdm
Project-URL: Repository, https://github.com/rlberry-py
